MANIFEST.in
README.txt
setup.py
cmsplugin_flickr/__init__.py
cmsplugin_flickr/cms_plugins.py
cmsplugin_flickr/models.py
cmsplugin_flickr.egg-info/PKG-INFO
cmsplugin_flickr.egg-info/SOURCES.txt
cmsplugin_flickr.egg-info/dependency_links.txt
cmsplugin_flickr.egg-info/not-zip-safe
cmsplugin_flickr.egg-info/requires.txt
cmsplugin_flickr.egg-info/top_level.txt
cmsplugin_flickr/templates/cms_plugins/flickr_cms_plugin.html