Metadata-Version: 1.0
Name: cmsplugin-flickr
Version: 0.1.2.1
Summary: flickr plugin for django-cms
Home-page: UNKNOWN
Author: Bernhard Vallant
Author-email: UNKNOWN
License: UNKNOWN
Platform: UNKNOWN
